AUTHORS
LICENSE
MANIFEST.in
setup.py
django_startappextracontext.egg-info/PKG-INFO
django_startappextracontext.egg-info/SOURCES.txt
django_startappextracontext.egg-info/dependency_links.txt
django_startappextracontext.egg-info/not-zip-safe
django_startappextracontext.egg-info/top_level.txt
startappextracontext/__init__.py
startappextracontext/models.py
startappextracontext/management/__init__.py
startappextracontext/management/commands/__init__.py
startappextracontext/management/commands/startappextra.py