Metadata-Version: 1.0
Name: django-startappextracontext
Version: 0.1
Summary: A small django app that provides an enhanced startapp management command. 
Home-page: http://github.com/saevarom/startappextracontext
Author: Sævar Öfjörð Magnússon
Author-email: saevar@saevar.is
License: MIT
Platform: any
Classifier: Development Status :: 4 - Beta
Classifier: Intended Audience :: Developers
Classifier: License :: OSI Approved :: MIT License
Classifier: Operating System :: OS Independent
Classifier: Programming Language :: Python
Classifier: Topic :: Software Development :: Libraries :: Python Modules
Classifier: Framework :: Django
